[
  {
    "code": "23000",
    "pref": "aichi",
    "name": "所属未定地",
    "population": 7449403,
    "populationTrend": "微減",
    "rent": {
      "value": 57272,
      "unit": "円/月",
      "source": "住宅・土地統計調査（加重平均）",
      "asOf": "2023",
      "isEstimated": false
    },
    "landPrice": {
      "value": 0,
      "unit": "円/㎡",
      "source": "サンプル",
      "asOf": "-",
      "isEstimated": true
    },
    "waitlistChildren": {
      "value": 0,
      "unit": "人",
      "source": "こども家庭庁 保育所等関連状況取りまとめ",
      "asOf": "2024-04-01",
      "isEstimated": false
    },
    "hazard": {
      "hasFloodRisk": false,
      "hasLandslideRisk": false,
      "note": "顕著な災害想定区域なし",
      "source": "国土数値情報（reinfolib XKT026/029）",
      "asOf": "2024"
    },
    "amenities": {
      "stations": 0,
      "preschools": 0,
      "medicalFacilities": 0,
      "source": "国土数値情報（reinfolib XKT015/007/010）",
      "asOf": "令和5年度"
    }
  },
  {
    "code": "23100",
    "pref": "aichi",
    "name": "名古屋市",
    "population": 2345892,
    "populationTrend": "横ばい",
    "rent": {
      "value": 61156,
      "unit": "円/月",
      "source": "住宅・土地統計調査（加重平均）",
      "asOf": "2023",
      "isEstimated": false
    },
    "landPrice": {
      "value": 563745,
      "unit": "円/㎡",
      "source": "地価公示（住宅地平均）",
      "asOf": "2025",
      "isEstimated": false
    },
    "waitlistChildren": {
      "value": 0,
      "unit": "人",
      "source": "こども家庭庁 保育所等関連状況取りまとめ",
      "asOf": "2024-04-01",
      "isEstimated": false
    },
    "hazard": {
      "hasFloodRisk": true,
      "hasLandslideRisk": true,
      "note": "浸水想定区域あり / 土砂災害警戒区域あり",
      "source": "国土数値情報（reinfolib XKT026/029）",
      "asOf": "2024"
    },
    "amenities": {
      "stations": 186,
      "preschools": 994,
      "medicalFacilities": 3750,
      "source": "国土数値情報（reinfolib XKT015/007/010）",
      "asOf": "令和5年度"
    }
  },
  {
    "code": "23201",
    "pref": "aichi",
    "name": "豊橋市",
    "population": 360031,
    "populationTrend": "減少",
    "rent": {
      "value": 50696,
      "unit": "円/月",
      "source": "住宅・土地統計調査（加重平均）",
      "asOf": "2023",
      "isEstimated": false
    },
    "landPrice": {
      "value": 99607,
      "unit": "円/㎡",
      "source": "地価公示（住宅地平均）",
      "asOf": "2025",
      "isEstimated": false
    },
    "waitlistChildren": {
      "value": 0,
      "unit": "人",
      "source": "こども家庭庁 保育所等関連状況取りまとめ",
      "asOf": "2024-04-01",
      "isEstimated": false
    },
    "hazard": {
      "hasFloodRisk": true,
      "hasLandslideRisk": true,
      "note": "浸水想定区域あり / 土砂災害警戒区域あり",
      "source": "国土数値情報（reinfolib XKT026/029）",
      "asOf": "2024"
    },
    "amenities": {
      "stations": 33,
      "preschools": 107,
      "medicalFacilities": 459,
      "source": "国土数値情報（reinfolib XKT015/007/010）",
      "asOf": "令和5年度"
    }
  },
  {
    "code": "23202",
    "pref": "aichi",
    "name": "岡崎市",
    "population": 377608,
    "populationTrend": "微減",
    "rent": {
      "value": 54458,
      "unit": "円/月",
      "source": "住宅・土地統計調査（加重平均）",
      "asOf": "2023",
      "isEstimated": false
    },
    "landPrice": {
      "value": 119011,
      "unit": "円/㎡",
      "source": "地価公示（住宅地平均）",
      "asOf": "2025",
      "isEstimated": false
    },
    "waitlistChildren": {
      "value": 19,
      "unit": "人",
      "source": "こども家庭庁 保育所等関連状況取りまとめ",
      "asOf": "2024-04-01",
      "isEstimated": false
    },
    "hazard": {
      "hasFloodRisk": true,
      "hasLandslideRisk": true,
      "note": "浸水想定区域あり / 土砂災害警戒区域あり",
      "source": "国土数値情報（reinfolib XKT026/029）",
      "asOf": "2024"
    },
    "amenities": {
      "stations": 17,
      "preschools": 102,
      "medicalFacilities": 412,
      "source": "国土数値情報（reinfolib XKT015/007/010）",
      "asOf": "令和5年度"
    }
  },
  {
    "code": "23203",
    "pref": "aichi",
    "name": "一宮市",
    "population": 368755,
    "populationTrend": "微減",
    "rent": {
      "value": 51441,
      "unit": "円/月",
      "source": "住宅・土地統計調査（加重平均）",
      "asOf": "2023",
      "isEstimated": false
    },
    "landPrice": {
      "value": 104136,
      "unit": "円/㎡",
      "source": "地価公示（住宅地平均）",
      "asOf": "2025",
      "isEstimated": false
    },
    "waitlistChildren": {
      "value": 0,
      "unit": "人",
      "source": "こども家庭庁 保育所等関連状況取りまとめ",
      "asOf": "2024-04-01",
      "isEstimated": false
    },
    "hazard": {
      "hasFloodRisk": true,
      "hasLandslideRisk": false,
      "note": "浸水想定区域あり",
      "source": "国土数値情報（reinfolib XKT026/029）",
      "asOf": "2024"
    },
    "amenities": {
      "stations": 20,
      "preschools": 114,
      "medicalFacilities": 458,
      "source": "国土数値情報（reinfolib XKT015/007/010）",
      "asOf": "令和5年度"
    }
  },
  {
    "code": "23204",
    "pref": "aichi",
    "name": "瀬戸市",
    "population": 123514,
    "populationTrend": "減少",
    "rent": {
      "value": 44377,
      "unit": "円/月",
      "source": "住宅・土地統計調査（加重平均）",
      "asOf": "2023",
      "isEstimated": false
    },
    "landPrice": {
      "value": 60307,
      "unit": "円/㎡",
      "source": "地価公示（住宅地平均）",
      "asOf": "2025",
      "isEstimated": false
    },
    "waitlistChildren": {
      "value": 7,
      "unit": "人",
      "source": "こども家庭庁 保育所等関連状況取りまとめ",
      "asOf": "2024-04-01",
      "isEstimated": false
    },
    "hazard": {
      "hasFloodRisk": true,
      "hasLandslideRisk": true,
      "note": "浸水想定区域あり / 土砂災害警戒区域あり",
      "source": "国土数値情報（reinfolib XKT026/029）",
      "asOf": "2024"
    },
    "amenities": {
      "stations": 8,
      "preschools": 7,
      "medicalFacilities": 134,
      "source": "国土数値情報（reinfolib XKT015/007/010）",
      "asOf": "令和5年度"
    }
  },
  {
    "code": "23205",
    "pref": "aichi",
    "name": "半田市",
    "population": 113533,
    "populationTrend": "減少",
    "rent": {
      "value": 51835,
      "unit": "円/月",
      "source": "住宅・土地統計調査（加重平均）",
      "asOf": "2023",
      "isEstimated": false
    },
    "landPrice": {
      "value": 81824,
      "unit": "円/㎡",
      "source": "地価公示（住宅地平均）",
      "asOf": "2025",
      "isEstimated": false
    },
    "waitlistChildren": {
      "value": 0,
      "unit": "人",
      "source": "こども家庭庁 保育所等関連状況取りまとめ",
      "asOf": "2024-04-01",
      "isEstimated": false
    },
    "hazard": {
      "hasFloodRisk": true,
      "hasLandslideRisk": true,
      "note": "浸水想定区域あり / 土砂災害警戒区域あり",
      "source": "国土数値情報（reinfolib XKT026/029）",
      "asOf": "2024"
    },
    "amenities": {
      "stations": 9,
      "preschools": 9,
      "medicalFacilities": 138,
      "source": "国土数値情報（reinfolib XKT015/007/010）",
      "asOf": "令和5年度"
    }
  },
  {
    "code": "23206",
    "pref": "aichi",
    "name": "春日井市",
    "population": 303120,
    "populationTrend": "微減",
    "rent": {
      "value": 57004,
      "unit": "円/月",
      "source": "住宅・土地統計調査（加重平均）",
      "asOf": "2023",
      "isEstimated": false
    },
    "landPrice": {
      "value": 125916,
      "unit": "円/㎡",
      "source": "地価公示（住宅地平均）",
      "asOf": "2025",
      "isEstimated": false
    },
    "waitlistChildren": {
      "value": 0,
      "unit": "人",
      "source": "こども家庭庁 保育所等関連状況取りまとめ",
      "asOf": "2024-04-01",
      "isEstimated": false
    },
    "hazard": {
      "hasFloodRisk": true,
      "hasLandslideRisk": true,
      "note": "浸水想定区域あり / 土砂災害警戒区域あり",
      "source": "国土数値情報（reinfolib XKT026/029）",
      "asOf": "2024"
    },
    "amenities": {
      "stations": 12,
      "preschools": 24,
      "medicalFacilities": 359,
      "source": "国土数値情報（reinfolib XKT015/007/010）",
      "asOf": "令和5年度"
    }
  },
  {
    "code": "23207",
    "pref": "aichi",
    "name": "豊川市",
    "population": 182525,
    "populationTrend": "微減",
    "rent": {
      "value": 49143,
      "unit": "円/月",
      "source": "住宅・土地統計調査（加重平均）",
      "asOf": "2023",
      "isEstimated": false
    },
    "landPrice": {
      "value": 77569,
      "unit": "円/㎡",
      "source": "地価公示（住宅地平均）",
      "asOf": "2025",
      "isEstimated": false
    },
    "waitlistChildren": {
      "value": 0,
      "unit": "人",
      "source": "こども家庭庁 保育所等関連状況取りまとめ",
      "asOf": "2024-04-01",
      "isEstimated": false
    },
    "hazard": {
      "hasFloodRisk": true,
      "hasLandslideRisk": true,
      "note": "浸水想定区域あり / 土砂災害警戒区域あり",
      "source": "国土数値情報（reinfolib XKT026/029）",
      "asOf": "2024"
    },
    "amenities": {
      "stations": 20,
      "preschools": 7,
      "medicalFacilities": 196,
      "source": "国土数値情報（reinfolib XKT015/007/010）",
      "asOf": "令和5年度"
    }
  },
  {
    "code": "23208",
    "pref": "aichi",
    "name": "津島市",
    "population": 57868,
    "populationTrend": "減少",
    "rent": {
      "value": 46387,
      "unit": "円/月",
      "source": "住宅・土地統計調査（加重平均）",
      "asOf": "2023",
      "isEstimated": false
    },
    "landPrice": {
      "value": 61921,
      "unit": "円/㎡",
      "source": "地価公示（住宅地平均）",
      "asOf": "2025",
      "isEstimated": false
    },
    "waitlistChildren": {
      "value": 0,
      "unit": "人",
      "source": "こども家庭庁 保育所等関連状況取りまとめ",
      "asOf": "2024-04-01",
      "isEstimated": false
    },
    "hazard": {
      "hasFloodRisk": true,
      "hasLandslideRisk": false,
      "note": "浸水想定区域あり",
      "source": "国土数値情報（reinfolib XKT026/029）",
      "asOf": "2024"
    },
    "amenities": {
      "stations": 3,
      "preschools": 14,
      "medicalFacilities": 92,
      "source": "国土数値情報（reinfolib XKT015/007/010）",
      "asOf": "令和5年度"
    }
  },
  {
    "code": "23209",
    "pref": "aichi",
    "name": "碧南市",
    "population": 71349,
    "populationTrend": "微減",
    "rent": {
      "value": 51844,
      "unit": "円/月",
      "source": "住宅・土地統計調査（加重平均）",
      "asOf": "2023",
      "isEstimated": false
    },
    "landPrice": {
      "value": 76492,
      "unit": "円/㎡",
      "source": "地価公示（住宅地平均）",
      "asOf": "2025",
      "isEstimated": false
    },
    "waitlistChildren": {
      "value": 0,
      "unit": "人",
      "source": "こども家庭庁 保育所等関連状況取りまとめ",
      "asOf": "2024-04-01",
      "isEstimated": false
    },
    "hazard": {
      "hasFloodRisk": true,
      "hasLandslideRisk": true,
      "note": "浸水想定区域あり / 土砂災害警戒区域あり",
      "source": "国土数値情報（reinfolib XKT026/029）",
      "asOf": "2024"
    },
    "amenities": {
      "stations": 4,
      "preschools": 8,
      "medicalFacilities": 83,
      "source": "国土数値情報（reinfolib XKT015/007/010）",
      "asOf": "令和5年度"
    }
  },
  {
    "code": "23210",
    "pref": "aichi",
    "name": "刈谷市",
    "population": 152807,
    "populationTrend": "横ばい",
    "rent": {
      "value": 56872,
      "unit": "円/月",
      "source": "住宅・土地統計調査（加重平均）",
      "asOf": "2023",
      "isEstimated": false
    },
    "landPrice": {
      "value": 179851,
      "unit": "円/㎡",
      "source": "地価公示（住宅地平均）",
      "asOf": "2025",
      "isEstimated": false
    },
    "waitlistChildren": {
      "value": 10,
      "unit": "人",
      "source": "こども家庭庁 保育所等関連状況取りまとめ",
      "asOf": "2024-04-01",
      "isEstimated": false
    },
    "hazard": {
      "hasFloodRisk": true,
      "hasLandslideRisk": true,
      "note": "浸水想定区域あり / 土砂災害警戒区域あり",
      "source": "国土数値情報（reinfolib XKT026/029）",
      "asOf": "2024"
    },
    "amenities": {
      "stations": 9,
      "preschools": 17,
      "medicalFacilities": 160,
      "source": "国土数値情報（reinfolib XKT015/007/010）",
      "asOf": "令和5年度"
    }
  },
  {
    "code": "23211",
    "pref": "aichi",
    "name": "豊田市",
    "population": 412230,
    "populationTrend": "微減",
    "rent": {
      "value": 53942,
      "unit": "円/月",
      "source": "住宅・土地統計調査（加重平均）",
      "asOf": "2023",
      "isEstimated": false
    },
    "landPrice": {
      "value": 126123,
      "unit": "円/㎡",
      "source": "地価公示（住宅地平均）",
      "asOf": "2025",
      "isEstimated": false
    },
    "waitlistChildren": {
      "value": 0,
      "unit": "人",
      "source": "こども家庭庁 保育所等関連状況取りまとめ",
      "asOf": "2024-04-01",
      "isEstimated": false
    },
    "hazard": {
      "hasFloodRisk": true,
      "hasLandslideRisk": true,
      "note": "浸水想定区域あり / 土砂災害警戒区域あり",
      "source": "国土数値情報（reinfolib XKT026/029）",
      "asOf": "2024"
    },
    "amenities": {
      "stations": 27,
      "preschools": 131,
      "medicalFacilities": 395,
      "source": "国土数値情報（reinfolib XKT015/007/010）",
      "asOf": "令和5年度"
    }
  },
  {
    "code": "23212",
    "pref": "aichi",
    "name": "安城市",
    "population": 186353,
    "populationTrend": "横ばい",
    "rent": {
      "value": 58689,
      "unit": "円/月",
      "source": "住宅・土地統計調査（加重平均）",
      "asOf": "2023",
      "isEstimated": false
    },
    "landPrice": {
      "value": 165800,
      "unit": "円/㎡",
      "source": "地価公示（住宅地平均）",
      "asOf": "2025",
      "isEstimated": false
    },
    "waitlistChildren": {
      "value": 0,
      "unit": "人",
      "source": "こども家庭庁 保育所等関連状況取りまとめ",
      "asOf": "2024-04-01",
      "isEstimated": false
    },
    "hazard": {
      "hasFloodRisk": true,
      "hasLandslideRisk": true,
      "note": "浸水想定区域あり / 土砂災害警戒区域あり",
      "source": "国土数値情報（reinfolib XKT026/029）",
      "asOf": "2024"
    },
    "amenities": {
      "stations": 11,
      "preschools": 23,
      "medicalFacilities": 206,
      "source": "国土数値情報（reinfolib XKT015/007/010）",
      "asOf": "令和5年度"
    }
  },
  {
    "code": "23213",
    "pref": "aichi",
    "name": "西尾市",
    "population": 166200,
    "populationTrend": "微減",
    "rent": {
      "value": 50299,
      "unit": "円/月",
      "source": "住宅・土地統計調査（加重平均）",
      "asOf": "2023",
      "isEstimated": false
    },
    "landPrice": {
      "value": 65620,
      "unit": "円/㎡",
      "source": "地価公示（住宅地平均）",
      "asOf": "2025",
      "isEstimated": false
    },
    "waitlistChildren": {
      "value": 0,
      "unit": "人",
      "source": "こども家庭庁 保育所等関連状況取りまとめ",
      "asOf": "2024-04-01",
      "isEstimated": false
    },
    "hazard": {
      "hasFloodRisk": true,
      "hasLandslideRisk": true,
      "note": "浸水想定区域あり / 土砂災害警戒区域あり",
      "source": "国土数値情報（reinfolib XKT026/029）",
      "asOf": "2024"
    },
    "amenities": {
      "stations": 12,
      "preschools": 9,
      "medicalFacilities": 163,
      "source": "国土数値情報（reinfolib XKT015/007/010）",
      "asOf": "令和5年度"
    }
  },
  {
    "code": "23214",
    "pref": "aichi",
    "name": "蒲郡市",
    "population": 74931,
    "populationTrend": "減少",
    "rent": {
      "value": 49641,
      "unit": "円/月",
      "source": "住宅・土地統計調査（加重平均）",
      "asOf": "2023",
      "isEstimated": false
    },
    "landPrice": {
      "value": 66948,
      "unit": "円/㎡",
      "source": "地価公示（住宅地平均）",
      "asOf": "2025",
      "isEstimated": false
    },
    "waitlistChildren": {
      "value": 0,
      "unit": "人",
      "source": "こども家庭庁 保育所等関連状況取りまとめ",
      "asOf": "2024-04-01",
      "isEstimated": false
    },
    "hazard": {
      "hasFloodRisk": false,
      "hasLandslideRisk": true,
      "note": "土砂災害警戒区域あり",
      "source": "国土数値情報（reinfolib XKT026/029）",
      "asOf": "2024"
    },
    "amenities": {
      "stations": 9,
      "preschools": 4,
      "medicalFacilities": 106,
      "source": "国土数値情報（reinfolib XKT015/007/010）",
      "asOf": "令和5年度"
    }
  },
  {
    "code": "23215",
    "pref": "aichi",
    "name": "犬山市",
    "population": 69940,
    "populationTrend": "減少",
    "rent": {
      "value": 53919,
      "unit": "円/月",
      "source": "住宅・土地統計調査（加重平均）",
      "asOf": "2023",
      "isEstimated": false
    },
    "landPrice": {
      "value": 69155,
      "unit": "円/㎡",
      "source": "地価公示（住宅地平均）",
      "asOf": "2025",
      "isEstimated": false
    },
    "waitlistChildren": {
      "value": 0,
      "unit": "人",
      "source": "こども家庭庁 保育所等関連状況取りまとめ",
      "asOf": "2024-04-01",
      "isEstimated": false
    },
    "hazard": {
      "hasFloodRisk": true,
      "hasLandslideRisk": true,
      "note": "浸水想定区域あり / 土砂災害警戒区域あり",
      "source": "国土数値情報（reinfolib XKT026/029）",
      "asOf": "2024"
    },
    "amenities": {
      "stations": 9,
      "preschools": 5,
      "medicalFacilities": 83,
      "source": "国土数値情報（reinfolib XKT015/007/010）",
      "asOf": "令和5年度"
    }
  },
  {
    "code": "23216",
    "pref": "aichi",
    "name": "常滑市",
    "population": 57832,
    "populationTrend": "微減",
    "rent": {
      "value": 47085,
      "unit": "円/月",
      "source": "住宅・土地統計調査（加重平均）",
      "asOf": "2023",
      "isEstimated": false
    },
    "landPrice": {
      "value": 50458,
      "unit": "円/㎡",
      "source": "地価公示（住宅地平均）",
      "asOf": "2025",
      "isEstimated": false
    },
    "waitlistChildren": {
      "value": 0,
      "unit": "人",
      "source": "こども家庭庁 保育所等関連状況取りまとめ",
      "asOf": "2024-04-01",
      "isEstimated": false
    },
    "hazard": {
      "hasFloodRisk": false,
      "hasLandslideRisk": true,
      "note": "土砂災害警戒区域あり",
      "source": "国土数値情報（reinfolib XKT026/029）",
      "asOf": "2024"
    },
    "amenities": {
      "stations": 9,
      "preschools": 6,
      "medicalFacilities": 63,
      "source": "国土数値情報（reinfolib XKT015/007/010）",
      "asOf": "令和5年度"
    }
  },
  {
    "code": "23217",
    "pref": "aichi",
    "name": "江南市",
    "population": 94137,
    "populationTrend": "減少",
    "rent": {
      "value": 46805,
      "unit": "円/月",
      "source": "住宅・土地統計調査（加重平均）",
      "asOf": "2023",
      "isEstimated": false
    },
    "landPrice": {
      "value": 91079,
      "unit": "円/㎡",
      "source": "地価公示（住宅地平均）",
      "asOf": "2025",
      "isEstimated": false
    },
    "waitlistChildren": {
      "value": 0,
      "unit": "人",
      "source": "こども家庭庁 保育所等関連状況取りまとめ",
      "asOf": "2024-04-01",
      "isEstimated": false
    },
    "hazard": {
      "hasFloodRisk": true,
      "hasLandslideRisk": false,
      "note": "浸水想定区域あり",
      "source": "国土数値情報（reinfolib XKT026/029）",
      "asOf": "2024"
    },
    "amenities": {
      "stations": 2,
      "preschools": 4,
      "medicalFacilities": 129,
      "source": "国土数値情報（reinfolib XKT015/007/010）",
      "asOf": "令和5年度"
    }
  },
  {
    "code": "23219",
    "pref": "aichi",
    "name": "小牧市",
    "population": 144181,
    "populationTrend": "減少",
    "rent": {
      "value": 53478,
      "unit": "円/月",
      "source": "住宅・土地統計調査（加重平均）",
      "asOf": "2023",
      "isEstimated": false
    },
    "landPrice": {
      "value": 91977,
      "unit": "円/㎡",
      "source": "地価公示（住宅地平均）",
      "asOf": "2025",
      "isEstimated": false
    },
    "waitlistChildren": {
      "value": 0,
      "unit": "人",
      "source": "こども家庭庁 保育所等関連状況取りまとめ",
      "asOf": "2024-04-01",
      "isEstimated": false
    },
    "hazard": {
      "hasFloodRisk": true,
      "hasLandslideRisk": true,
      "note": "浸水想定区域あり / 土砂災害警戒区域あり",
      "source": "国土数値情報（reinfolib XKT026/029）",
      "asOf": "2024"
    },
    "amenities": {
      "stations": 5,
      "preschools": 11,
      "medicalFacilities": 167,
      "source": "国土数値情報（reinfolib XKT015/007/010）",
      "asOf": "令和5年度"
    }
  },
  {
    "code": "23220",
    "pref": "aichi",
    "name": "稲沢市",
    "population": 129885,
    "populationTrend": "減少",
    "rent": {
      "value": 51876,
      "unit": "円/月",
      "source": "住宅・土地統計調査（加重平均）",
      "asOf": "2023",
      "isEstimated": false
    },
    "landPrice": {
      "value": 94958,
      "unit": "円/㎡",
      "source": "地価公示（住宅地平均）",
      "asOf": "2025",
      "isEstimated": false
    },
    "waitlistChildren": {
      "value": 0,
      "unit": "人",
      "source": "こども家庭庁 保育所等関連状況取りまとめ",
      "asOf": "2024-04-01",
      "isEstimated": false
    },
    "hazard": {
      "hasFloodRisk": true,
      "hasLandslideRisk": false,
      "note": "浸水想定区域あり",
      "source": "国土数値情報（reinfolib XKT026/029）",
      "asOf": "2024"
    },
    "amenities": {
      "stations": 10,
      "preschools": 7,
      "medicalFacilities": 170,
      "source": "国土数値情報（reinfolib XKT015/007/010）",
      "asOf": "令和5年度"
    }
  },
  {
    "code": "23221",
    "pref": "aichi",
    "name": "新城市",
    "population": 40664,
    "populationTrend": "減少",
    "rent": {
      "value": 42644,
      "unit": "円/月",
      "source": "住宅・土地統計調査（加重平均）",
      "asOf": "2023",
      "isEstimated": false
    },
    "landPrice": {
      "value": 45663,
      "unit": "円/㎡",
      "source": "地価公示（住宅地平均）",
      "asOf": "2025",
      "isEstimated": false
    },
    "waitlistChildren": {
      "value": 0,
      "unit": "人",
      "source": "こども家庭庁 保育所等関連状況取りまとめ",
      "asOf": "2024-04-01",
      "isEstimated": false
    },
    "hazard": {
      "hasFloodRisk": true,
      "hasLandslideRisk": true,
      "note": "浸水想定区域あり / 土砂災害警戒区域あり",
      "source": "国土数値情報（reinfolib XKT026/029）",
      "asOf": "2024"
    },
    "amenities": {
      "stations": 14,
      "preschools": 0,
      "medicalFacilities": 63,
      "source": "国土数値情報（reinfolib XKT015/007/010）",
      "asOf": "令和5年度"
    }
  },
  {
    "code": "23222",
    "pref": "aichi",
    "name": "東海市",
    "population": 112487,
    "populationTrend": "微減",
    "rent": {
      "value": 55062,
      "unit": "円/月",
      "source": "住宅・土地統計調査（加重平均）",
      "asOf": "2023",
      "isEstimated": false
    },
    "landPrice": {
      "value": 106214,
      "unit": "円/㎡",
      "source": "地価公示（住宅地平均）",
      "asOf": "2025",
      "isEstimated": false
    },
    "waitlistChildren": {
      "value": 0,
      "unit": "人",
      "source": "こども家庭庁 保育所等関連状況取りまとめ",
      "asOf": "2024-04-01",
      "isEstimated": false
    },
    "hazard": {
      "hasFloodRisk": false,
      "hasLandslideRisk": true,
      "note": "土砂災害警戒区域あり",
      "source": "国土数値情報（reinfolib XKT026/029）",
      "asOf": "2024"
    },
    "amenities": {
      "stations": 10,
      "preschools": 5,
      "medicalFacilities": 128,
      "source": "国土数値情報（reinfolib XKT015/007/010）",
      "asOf": "令和5年度"
    }
  },
  {
    "code": "23223",
    "pref": "aichi",
    "name": "大府市",
    "population": 92485,
    "populationTrend": "横ばい",
    "rent": {
      "value": 57453,
      "unit": "円/月",
      "source": "住宅・土地統計調査（加重平均）",
      "asOf": "2023",
      "isEstimated": false
    },
    "landPrice": {
      "value": 145348,
      "unit": "円/㎡",
      "source": "地価公示（住宅地平均）",
      "asOf": "2025",
      "isEstimated": false
    },
    "waitlistChildren": {
      "value": 0,
      "unit": "人",
      "source": "こども家庭庁 保育所等関連状況取りまとめ",
      "asOf": "2024-04-01",
      "isEstimated": false
    },
    "hazard": {
      "hasFloodRisk": false,
      "hasLandslideRisk": true,
      "note": "土砂災害警戒区域あり",
      "source": "国土数値情報（reinfolib XKT026/029）",
      "asOf": "2024"
    },
    "amenities": {
      "stations": 3,
      "preschools": 5,
      "medicalFacilities": 103,
      "source": "国土数値情報（reinfolib XKT015/007/010）",
      "asOf": "令和5年度"
    }
  },
  {
    "code": "23224",
    "pref": "aichi",
    "name": "知多市",
    "population": 82095,
    "populationTrend": "微減",
    "rent": {
      "value": 49694,
      "unit": "円/月",
      "source": "住宅・土地統計調査（加重平均）",
      "asOf": "2023",
      "isEstimated": false
    },
    "landPrice": {
      "value": 70054,
      "unit": "円/㎡",
      "source": "地価公示（住宅地平均）",
      "asOf": "2025",
      "isEstimated": false
    },
    "waitlistChildren": {
      "value": 0,
      "unit": "人",
      "source": "こども家庭庁 保育所等関連状況取りまとめ",
      "asOf": "2024-04-01",
      "isEstimated": false
    },
    "hazard": {
      "hasFloodRisk": true,
      "hasLandslideRisk": true,
      "note": "浸水想定区域あり / 土砂災害警戒区域あり",
      "source": "国土数値情報（reinfolib XKT026/029）",
      "asOf": "2024"
    },
    "amenities": {
      "stations": 6,
      "preschools": 6,
      "medicalFacilities": 80,
      "source": "国土数値情報（reinfolib XKT015/007/010）",
      "asOf": "令和5年度"
    }
  },
  {
    "code": "23225",
    "pref": "aichi",
    "name": "知立市",
    "population": 72568,
    "populationTrend": "横ばい",
    "rent": {
      "value": 56634,
      "unit": "円/月",
      "source": "住宅・土地統計調査（加重平均）",
      "asOf": "2023",
      "isEstimated": false
    },
    "landPrice": {
      "value": 162294,
      "unit": "円/㎡",
      "source": "地価公示（住宅地平均）",
      "asOf": "2025",
      "isEstimated": false
    },
    "waitlistChildren": {
      "value": 0,
      "unit": "人",
      "source": "こども家庭庁 保育所等関連状況取りまとめ",
      "asOf": "2024-04-01",
      "isEstimated": false
    },
    "hazard": {
      "hasFloodRisk": true,
      "hasLandslideRisk": false,
      "note": "浸水想定区域あり",
      "source": "国土数値情報（reinfolib XKT026/029）",
      "asOf": "2024"
    },
    "amenities": {
      "stations": 5,
      "preschools": 5,
      "medicalFacilities": 65,
      "source": "国土数値情報（reinfolib XKT015/007/010）",
      "asOf": "令和5年度"
    }
  },
  {
    "code": "23226",
    "pref": "aichi",
    "name": "尾張旭市",
    "population": 82469,
    "populationTrend": "横ばい",
    "rent": {
      "value": 59361,
      "unit": "円/月",
      "source": "住宅・土地統計調査（加重平均）",
      "asOf": "2023",
      "isEstimated": false
    },
    "landPrice": {
      "value": 111159,
      "unit": "円/㎡",
      "source": "地価公示（住宅地平均）",
      "asOf": "2025",
      "isEstimated": false
    },
    "waitlistChildren": {
      "value": 15,
      "unit": "人",
      "source": "こども家庭庁 保育所等関連状況取りまとめ",
      "asOf": "2024-04-01",
      "isEstimated": false
    },
    "hazard": {
      "hasFloodRisk": true,
      "hasLandslideRisk": true,
      "note": "浸水想定区域あり / 土砂災害警戒区域あり",
      "source": "国土数値情報（reinfolib XKT026/029）",
      "asOf": "2024"
    },
    "amenities": {
      "stations": 4,
      "preschools": 5,
      "medicalFacilities": 116,
      "source": "国土数値情報（reinfolib XKT015/007/010）",
      "asOf": "令和5年度"
    }
  },
  {
    "code": "23227",
    "pref": "aichi",
    "name": "高浜市",
    "population": 48122,
    "populationTrend": "増加",
    "rent": {
      "value": 47182,
      "unit": "円/月",
      "source": "住宅・土地統計調査（加重平均）",
      "asOf": "2023",
      "isEstimated": false
    },
    "landPrice": {
      "value": 97592,
      "unit": "円/㎡",
      "source": "地価公示（住宅地平均）",
      "asOf": "2025",
      "isEstimated": false
    },
    "waitlistChildren": {
      "value": 0,
      "unit": "人",
      "source": "こども家庭庁 保育所等関連状況取りまとめ",
      "asOf": "2024-04-01",
      "isEstimated": false
    },
    "hazard": {
      "hasFloodRisk": true,
      "hasLandslideRisk": true,
      "note": "浸水想定区域あり / 土砂災害警戒区域あり",
      "source": "国土数値情報（reinfolib XKT026/029）",
      "asOf": "2024"
    },
    "amenities": {
      "stations": 3,
      "preschools": 6,
      "medicalFacilities": 41,
      "source": "国土数値情報（reinfolib XKT015/007/010）",
      "asOf": "令和5年度"
    }
  },
  {
    "code": "23228",
    "pref": "aichi",
    "name": "岩倉市",
    "population": 47386,
    "populationTrend": "微減",
    "rent": {
      "value": 57131,
      "unit": "円/月",
      "source": "住宅・土地統計調査（加重平均）",
      "asOf": "2023",
      "isEstimated": false
    },
    "landPrice": {
      "value": 113847,
      "unit": "円/㎡",
      "source": "地価公示（住宅地平均）",
      "asOf": "2025",
      "isEstimated": false
    },
    "waitlistChildren": {
      "value": 6,
      "unit": "人",
      "source": "こども家庭庁 保育所等関連状況取りまとめ",
      "asOf": "2024-04-01",
      "isEstimated": false
    },
    "hazard": {
      "hasFloodRisk": true,
      "hasLandslideRisk": false,
      "note": "浸水想定区域あり",
      "source": "国土数値情報（reinfolib XKT026/029）",
      "asOf": "2024"
    },
    "amenities": {
      "stations": 3,
      "preschools": 5,
      "medicalFacilities": 57,
      "source": "国土数値情報（reinfolib XKT015/007/010）",
      "asOf": "令和5年度"
    }
  },
  {
    "code": "23229",
    "pref": "aichi",
    "name": "豊明市",
    "population": 68382,
    "populationTrend": "微減",
    "rent": {
      "value": 57396,
      "unit": "円/月",
      "source": "住宅・土地統計調査（加重平均）",
      "asOf": "2023",
      "isEstimated": false
    },
    "landPrice": {
      "value": 127536,
      "unit": "円/㎡",
      "source": "地価公示（住宅地平均）",
      "asOf": "2025",
      "isEstimated": false
    },
    "waitlistChildren": {
      "value": 0,
      "unit": "人",
      "source": "こども家庭庁 保育所等関連状況取りまとめ",
      "asOf": "2024-04-01",
      "isEstimated": false
    },
    "hazard": {
      "hasFloodRisk": false,
      "hasLandslideRisk": true,
      "note": "土砂災害警戒区域あり",
      "source": "国土数値情報（reinfolib XKT026/029）",
      "asOf": "2024"
    },
    "amenities": {
      "stations": 2,
      "preschools": 5,
      "medicalFacilities": 79,
      "source": "国土数値情報（reinfolib XKT015/007/010）",
      "asOf": "令和5年度"
    }
  },
  {
    "code": "23230",
    "pref": "aichi",
    "name": "日進市",
    "population": 94740,
    "populationTrend": "増加",
    "rent": {
      "value": 61241,
      "unit": "円/月",
      "source": "住宅・土地統計調査（加重平均）",
      "asOf": "2023",
      "isEstimated": false
    },
    "landPrice": {
      "value": 147806,
      "unit": "円/㎡",
      "source": "地価公示（住宅地平均）",
      "asOf": "2025",
      "isEstimated": false
    },
    "waitlistChildren": {
      "value": 0,
      "unit": "人",
      "source": "こども家庭庁 保育所等関連状況取りまとめ",
      "asOf": "2024-04-01",
      "isEstimated": false
    },
    "hazard": {
      "hasFloodRisk": true,
      "hasLandslideRisk": true,
      "note": "浸水想定区域あり / 土砂災害警戒区域あり",
      "source": "国土数値情報（reinfolib XKT026/029）",
      "asOf": "2024"
    },
    "amenities": {
      "stations": 4,
      "preschools": 7,
      "medicalFacilities": 132,
      "source": "国土数値情報（reinfolib XKT015/007/010）",
      "asOf": "令和5年度"
    }
  },
  {
    "code": "23231",
    "pref": "aichi",
    "name": "田原市",
    "population": 56352,
    "populationTrend": "減少",
    "rent": {
      "value": 46682,
      "unit": "円/月",
      "source": "住宅・土地統計調査（加重平均）",
      "asOf": "2023",
      "isEstimated": false
    },
    "landPrice": {
      "value": 41348,
      "unit": "円/㎡",
      "source": "地価公示（住宅地平均）",
      "asOf": "2025",
      "isEstimated": false
    },
    "waitlistChildren": {
      "value": 0,
      "unit": "人",
      "source": "こども家庭庁 保育所等関連状況取りまとめ",
      "asOf": "2024-04-01",
      "isEstimated": false
    },
    "hazard": {
      "hasFloodRisk": false,
      "hasLandslideRisk": true,
      "note": "土砂災害警戒区域あり",
      "source": "国土数値情報（reinfolib XKT026/029）",
      "asOf": "2024"
    },
    "amenities": {
      "stations": 4,
      "preschools": 4,
      "medicalFacilities": 61,
      "source": "国土数値情報（reinfolib XKT015/007/010）",
      "asOf": "令和5年度"
    }
  },
  {
    "code": "23232",
    "pref": "aichi",
    "name": "愛西市",
    "population": 57808,
    "populationTrend": "減少",
    "rent": {
      "value": 53310,
      "unit": "円/月",
      "source": "住宅・土地統計調査（加重平均）",
      "asOf": "2023",
      "isEstimated": false
    },
    "landPrice": {
      "value": 51620,
      "unit": "円/㎡",
      "source": "地価公示（住宅地平均）",
      "asOf": "2025",
      "isEstimated": false
    },
    "waitlistChildren": {
      "value": 0,
      "unit": "人",
      "source": "こども家庭庁 保育所等関連状況取りまとめ",
      "asOf": "2024-04-01",
      "isEstimated": false
    },
    "hazard": {
      "hasFloodRisk": true,
      "hasLandslideRisk": false,
      "note": "浸水想定区域あり",
      "source": "国土数値情報（reinfolib XKT026/029）",
      "asOf": "2024"
    },
    "amenities": {
      "stations": 7,
      "preschools": 7,
      "medicalFacilities": 64,
      "source": "国土数値情報（reinfolib XKT015/007/010）",
      "asOf": "令和5年度"
    }
  },
  {
    "code": "23233",
    "pref": "aichi",
    "name": "清須市",
    "population": 68178,
    "populationTrend": "微増",
    "rent": {
      "value": 59040,
      "unit": "円/月",
      "source": "住宅・土地統計調査（加重平均）",
      "asOf": "2023",
      "isEstimated": false
    },
    "landPrice": {
      "value": 100871,
      "unit": "円/㎡",
      "source": "地価公示（住宅地平均）",
      "asOf": "2025",
      "isEstimated": false
    },
    "waitlistChildren": {
      "value": 0,
      "unit": "人",
      "source": "こども家庭庁 保育所等関連状況取りまとめ",
      "asOf": "2024-04-01",
      "isEstimated": false
    },
    "hazard": {
      "hasFloodRisk": true,
      "hasLandslideRisk": false,
      "note": "浸水想定区域あり",
      "source": "国土数値情報（reinfolib XKT026/029）",
      "asOf": "2024"
    },
    "amenities": {
      "stations": 11,
      "preschools": 4,
      "medicalFacilities": 81,
      "source": "国土数値情報（reinfolib XKT015/007/010）",
      "asOf": "令和5年度"
    }
  },
  {
    "code": "23234",
    "pref": "aichi",
    "name": "北名古屋市",
    "population": 85687,
    "populationTrend": "横ばい",
    "rent": {
      "value": 57572,
      "unit": "円/月",
      "source": "住宅・土地統計調査（加重平均）",
      "asOf": "2023",
      "isEstimated": false
    },
    "landPrice": {
      "value": 109477,
      "unit": "円/㎡",
      "source": "地価公示（住宅地平均）",
      "asOf": "2025",
      "isEstimated": false
    },
    "waitlistChildren": {
      "value": 0,
      "unit": "人",
      "source": "こども家庭庁 保育所等関連状況取りまとめ",
      "asOf": "2024-04-01",
      "isEstimated": false
    },
    "hazard": {
      "hasFloodRisk": true,
      "hasLandslideRisk": false,
      "note": "浸水想定区域あり",
      "source": "国土数値情報（reinfolib XKT026/029）",
      "asOf": "2024"
    },
    "amenities": {
      "stations": 2,
      "preschools": 7,
      "medicalFacilities": 87,
      "source": "国土数値情報（reinfolib XKT015/007/010）",
      "asOf": "令和5年度"
    }
  },
  {
    "code": "23235",
    "pref": "aichi",
    "name": "弥富市",
    "population": 42235,
    "populationTrend": "微減",
    "rent": {
      "value": 58298,
      "unit": "円/月",
      "source": "住宅・土地統計調査（加重平均）",
      "asOf": "2023",
      "isEstimated": false
    },
    "landPrice": {
      "value": 67442,
      "unit": "円/㎡",
      "source": "地価公示（住宅地平均）",
      "asOf": "2025",
      "isEstimated": false
    },
    "waitlistChildren": {
      "value": 0,
      "unit": "人",
      "source": "こども家庭庁 保育所等関連状況取りまとめ",
      "asOf": "2024-04-01",
      "isEstimated": false
    },
    "hazard": {
      "hasFloodRisk": true,
      "hasLandslideRisk": false,
      "note": "浸水想定区域あり",
      "source": "国土数値情報（reinfolib XKT026/029）",
      "asOf": "2024"
    },
    "amenities": {
      "stations": 5,
      "preschools": 1,
      "medicalFacilities": 54,
      "source": "国土数値情報（reinfolib XKT015/007/010）",
      "asOf": "令和5年度"
    }
  },
  {
    "code": "23236",
    "pref": "aichi",
    "name": "みよし市",
    "population": 61452,
    "populationTrend": "横ばい",
    "rent": {
      "value": 53181,
      "unit": "円/月",
      "source": "住宅・土地統計調査（加重平均）",
      "asOf": "2023",
      "isEstimated": false
    },
    "landPrice": {
      "value": 121530,
      "unit": "円/㎡",
      "source": "地価公示（住宅地平均）",
      "asOf": "2025",
      "isEstimated": false
    },
    "waitlistChildren": {
      "value": 0,
      "unit": "人",
      "source": "こども家庭庁 保育所等関連状況取りまとめ",
      "asOf": "2024-04-01",
      "isEstimated": false
    },
    "hazard": {
      "hasFloodRisk": false,
      "hasLandslideRisk": true,
      "note": "土砂災害警戒区域あり",
      "source": "国土数値情報（reinfolib XKT026/029）",
      "asOf": "2024"
    },
    "amenities": {
      "stations": 2,
      "preschools": 6,
      "medicalFacilities": 71,
      "source": "国土数値情報（reinfolib XKT015/007/010）",
      "asOf": "令和5年度"
    }
  },
  {
    "code": "23237",
    "pref": "aichi",
    "name": "あま市",
    "population": 86552,
    "populationTrend": "横ばい",
    "rent": {
      "value": 53924,
      "unit": "円/月",
      "source": "住宅・土地統計調査（加重平均）",
      "asOf": "2023",
      "isEstimated": false
    },
    "landPrice": {
      "value": 76174,
      "unit": "円/㎡",
      "source": "地価公示（住宅地平均）",
      "asOf": "2025",
      "isEstimated": false
    },
    "waitlistChildren": {
      "value": 0,
      "unit": "人",
      "source": "こども家庭庁 保育所等関連状況取りまとめ",
      "asOf": "2024-04-01",
      "isEstimated": false
    },
    "hazard": {
      "hasFloodRisk": true,
      "hasLandslideRisk": false,
      "note": "浸水想定区域あり",
      "source": "国土数値情報（reinfolib XKT026/029）",
      "asOf": "2024"
    },
    "amenities": {
      "stations": 3,
      "preschools": 9,
      "medicalFacilities": 85,
      "source": "国土数値情報（reinfolib XKT015/007/010）",
      "asOf": "令和5年度"
    }
  },
  {
    "code": "23238",
    "pref": "aichi",
    "name": "長久手市",
    "population": 63385,
    "populationTrend": "増加",
    "rent": {
      "value": 61432,
      "unit": "円/月",
      "source": "住宅・土地統計調査（加重平均）",
      "asOf": "2023",
      "isEstimated": false
    },
    "landPrice": {
      "value": 177167,
      "unit": "円/㎡",
      "source": "地価公示（住宅地平均）",
      "asOf": "2025",
      "isEstimated": false
    },
    "waitlistChildren": {
      "value": 0,
      "unit": "人",
      "source": "こども家庭庁 保育所等関連状況取りまとめ",
      "asOf": "2024-04-01",
      "isEstimated": false
    },
    "hazard": {
      "hasFloodRisk": true,
      "hasLandslideRisk": true,
      "note": "浸水想定区域あり / 土砂災害警戒区域あり",
      "source": "国土数値情報（reinfolib XKT026/029）",
      "asOf": "2024"
    },
    "amenities": {
      "stations": 6,
      "preschools": 3,
      "medicalFacilities": 75,
      "source": "国土数値情報（reinfolib XKT015/007/010）",
      "asOf": "令和5年度"
    }
  },
  {
    "code": "23302",
    "pref": "aichi",
    "name": "東郷町",
    "population": 43891,
    "populationTrend": "横ばい",
    "rent": {
      "value": 64129,
      "unit": "円/月",
      "source": "住宅・土地統計調査（加重平均）",
      "asOf": "2023",
      "isEstimated": false
    },
    "landPrice": {
      "value": 104213,
      "unit": "円/㎡",
      "source": "地価公示（住宅地平均）",
      "asOf": "2025",
      "isEstimated": false
    },
    "waitlistChildren": {
      "value": 0,
      "unit": "人",
      "source": "こども家庭庁 保育所等関連状況取りまとめ",
      "asOf": "2024-04-01",
      "isEstimated": false
    },
    "hazard": {
      "hasFloodRisk": false,
      "hasLandslideRisk": true,
      "note": "土砂災害警戒区域あり",
      "source": "国土数値情報（reinfolib XKT026/029）",
      "asOf": "2024"
    },
    "amenities": {
      "stations": 0,
      "preschools": 3,
      "medicalFacilities": 52,
      "source": "国土数値情報（reinfolib XKT015/007/010）",
      "asOf": "令和5年度"
    }
  },
  {
    "code": "23342",
    "pref": "aichi",
    "name": "豊山町",
    "population": 15775,
    "populationTrend": "微増",
    "rent": {
      "value": 57659,
      "unit": "円/月",
      "source": "住宅・土地統計調査（加重平均）",
      "asOf": "2023",
      "isEstimated": false
    },
    "landPrice": {
      "value": 96214,
      "unit": "円/㎡",
      "source": "地価公示（住宅地平均）",
      "asOf": "2025",
      "isEstimated": false
    },
    "waitlistChildren": {
      "value": 0,
      "unit": "人",
      "source": "こども家庭庁 保育所等関連状況取りまとめ",
      "asOf": "2024-04-01",
      "isEstimated": false
    },
    "hazard": {
      "hasFloodRisk": true,
      "hasLandslideRisk": false,
      "note": "浸水想定区域あり",
      "source": "国土数値情報（reinfolib XKT026/029）",
      "asOf": "2024"
    },
    "amenities": {
      "stations": 0,
      "preschools": 1,
      "medicalFacilities": 16,
      "source": "国土数値情報（reinfolib XKT015/007/010）",
      "asOf": "令和5年度"
    }
  },
  {
    "code": "23361",
    "pref": "aichi",
    "name": "大口町",
    "population": 23501,
    "populationTrend": "減少",
    "rent": {
      "value": 41333,
      "unit": "円/月",
      "source": "住宅・土地統計調査（加重平均）",
      "asOf": "2023",
      "isEstimated": false
    },
    "landPrice": {
      "value": 76617,
      "unit": "円/㎡",
      "source": "地価公示（住宅地平均）",
      "asOf": "2025",
      "isEstimated": false
    },
    "waitlistChildren": {
      "value": 0,
      "unit": "人",
      "source": "こども家庭庁 保育所等関連状況取りまとめ",
      "asOf": "2024-04-01",
      "isEstimated": false
    },
    "hazard": {
      "hasFloodRisk": true,
      "hasLandslideRisk": false,
      "note": "浸水想定区域あり",
      "source": "国土数値情報（reinfolib XKT026/029）",
      "asOf": "2024"
    },
    "amenities": {
      "stations": 0,
      "preschools": 2,
      "medicalFacilities": 27,
      "source": "国土数値情報（reinfolib XKT015/007/010）",
      "asOf": "令和5年度"
    }
  },
  {
    "code": "23362",
    "pref": "aichi",
    "name": "扶桑町",
    "population": 34136,
    "populationTrend": "横ばい",
    "rent": {
      "value": 56084,
      "unit": "円/月",
      "source": "住宅・土地統計調査（加重平均）",
      "asOf": "2023",
      "isEstimated": false
    },
    "landPrice": {
      "value": 77383,
      "unit": "円/㎡",
      "source": "地価公示（住宅地平均）",
      "asOf": "2025",
      "isEstimated": false
    },
    "waitlistChildren": {
      "value": 0,
      "unit": "人",
      "source": "こども家庭庁 保育所等関連状況取りまとめ",
      "asOf": "2024-04-01",
      "isEstimated": false
    },
    "hazard": {
      "hasFloodRisk": true,
      "hasLandslideRisk": false,
      "note": "浸水想定区域あり",
      "source": "国土数値情報（reinfolib XKT026/029）",
      "asOf": "2024"
    },
    "amenities": {
      "stations": 3,
      "preschools": 1,
      "medicalFacilities": 37,
      "source": "国土数値情報（reinfolib XKT015/007/010）",
      "asOf": "令和5年度"
    }
  },
  {
    "code": "23424",
    "pref": "aichi",
    "name": "大治町",
    "population": 32450,
    "populationTrend": "横ばい",
    "rent": {
      "value": 54233,
      "unit": "円/月",
      "source": "住宅・土地統計調査（加重平均）",
      "asOf": "2023",
      "isEstimated": false
    },
    "landPrice": {
      "value": 78357,
      "unit": "円/㎡",
      "source": "地価公示（住宅地平均）",
      "asOf": "2025",
      "isEstimated": false
    },
    "waitlistChildren": {
      "value": 0,
      "unit": "人",
      "source": "こども家庭庁 保育所等関連状況取りまとめ",
      "asOf": "2024-04-01",
      "isEstimated": false
    },
    "hazard": {
      "hasFloodRisk": true,
      "hasLandslideRisk": false,
      "note": "浸水想定区域あり",
      "source": "国土数値情報（reinfolib XKT026/029）",
      "asOf": "2024"
    },
    "amenities": {
      "stations": 0,
      "preschools": 3,
      "medicalFacilities": 23,
      "source": "国土数値情報（reinfolib XKT015/007/010）",
      "asOf": "令和5年度"
    }
  },
  {
    "code": "23425",
    "pref": "aichi",
    "name": "蟹江町",
    "population": 36471,
    "populationTrend": "微減",
    "rent": {
      "value": 63789,
      "unit": "円/月",
      "source": "住宅・土地統計調査（加重平均）",
      "asOf": "2023",
      "isEstimated": false
    },
    "landPrice": {
      "value": 91233,
      "unit": "円/㎡",
      "source": "地価公示（住宅地平均）",
      "asOf": "2025",
      "isEstimated": false
    },
    "waitlistChildren": {
      "value": 0,
      "unit": "人",
      "source": "こども家庭庁 保育所等関連状況取りまとめ",
      "asOf": "2024-04-01",
      "isEstimated": false
    },
    "hazard": {
      "hasFloodRisk": true,
      "hasLandslideRisk": false,
      "note": "浸水想定区域あり",
      "source": "国土数値情報（reinfolib XKT026/029）",
      "asOf": "2024"
    },
    "amenities": {
      "stations": 3,
      "preschools": 3,
      "medicalFacilities": 43,
      "source": "国土数値情報（reinfolib XKT015/007/010）",
      "asOf": "令和5年度"
    }
  },
  {
    "code": "23427",
    "pref": "aichi",
    "name": "飛島村",
    "population": 4410,
    "populationTrend": "減少",
    "rent": {
      "value": 0,
      "unit": "円/月",
      "source": "サンプル",
      "asOf": "-",
      "isEstimated": true
    },
    "landPrice": {
      "value": 53833,
      "unit": "円/㎡",
      "source": "地価公示（住宅地平均）",
      "asOf": "2025",
      "isEstimated": false
    },
    "waitlistChildren": {
      "value": 0,
      "unit": "人",
      "source": "こども家庭庁 保育所等関連状況取りまとめ",
      "asOf": "2024-04-01",
      "isEstimated": false
    },
    "hazard": {
      "hasFloodRisk": true,
      "hasLandslideRisk": false,
      "note": "浸水想定区域あり",
      "source": "国土数値情報（reinfolib XKT026/029）",
      "asOf": "2024"
    },
    "amenities": {
      "stations": 0,
      "preschools": 1,
      "medicalFacilities": 7,
      "source": "国土数値情報（reinfolib XKT015/007/010）",
      "asOf": "令和5年度"
    }
  },
  {
    "code": "23441",
    "pref": "aichi",
    "name": "阿久比町",
    "population": 27377,
    "populationTrend": "減少",
    "rent": {
      "value": 53870,
      "unit": "円/月",
      "source": "住宅・土地統計調査（加重平均）",
      "asOf": "2023",
      "isEstimated": false
    },
    "landPrice": {
      "value": 68017,
      "unit": "円/㎡",
      "source": "地価公示（住宅地平均）",
      "asOf": "2025",
      "isEstimated": false
    },
    "waitlistChildren": {
      "value": 0,
      "unit": "人",
      "source": "こども家庭庁 保育所等関連状況取りまとめ",
      "asOf": "2024-04-01",
      "isEstimated": false
    },
    "hazard": {
      "hasFloodRisk": true,
      "hasLandslideRisk": true,
      "note": "浸水想定区域あり / 土砂災害警戒区域あり",
      "source": "国土数値情報（reinfolib XKT026/029）",
      "asOf": "2024"
    },
    "amenities": {
      "stations": 5,
      "preschools": 2,
      "medicalFacilities": 31,
      "source": "国土数値情報（reinfolib XKT015/007/010）",
      "asOf": "令和5年度"
    }
  },
  {
    "code": "23442",
    "pref": "aichi",
    "name": "東浦町",
    "population": 48958,
    "populationTrend": "微減",
    "rent": {
      "value": 48414,
      "unit": "円/月",
      "source": "住宅・土地統計調査（加重平均）",
      "asOf": "2023",
      "isEstimated": false
    },
    "landPrice": {
      "value": 90900,
      "unit": "円/㎡",
      "source": "地価公示（住宅地平均）",
      "asOf": "2025",
      "isEstimated": false
    },
    "waitlistChildren": {
      "value": 0,
      "unit": "人",
      "source": "こども家庭庁 保育所等関連状況取りまとめ",
      "asOf": "2024-04-01",
      "isEstimated": false
    },
    "hazard": {
      "hasFloodRisk": false,
      "hasLandslideRisk": true,
      "note": "土砂災害警戒区域あり",
      "source": "国土数値情報（reinfolib XKT026/029）",
      "asOf": "2024"
    },
    "amenities": {
      "stations": 4,
      "preschools": 1,
      "medicalFacilities": 43,
      "source": "国土数値情報（reinfolib XKT015/007/010）",
      "asOf": "令和5年度"
    }
  },
  {
    "code": "23445",
    "pref": "aichi",
    "name": "南知多町",
    "population": 14452,
    "populationTrend": "減少",
    "rent": {
      "value": 38286,
      "unit": "円/月",
      "source": "住宅・土地統計調査（加重平均）",
      "asOf": "2023",
      "isEstimated": false
    },
    "landPrice": {
      "value": 21100,
      "unit": "円/㎡",
      "source": "地価公示（住宅地平均）",
      "asOf": "2025",
      "isEstimated": false
    },
    "waitlistChildren": {
      "value": 0,
      "unit": "人",
      "source": "こども家庭庁 保育所等関連状況取りまとめ",
      "asOf": "2024-04-01",
      "isEstimated": false
    },
    "hazard": {
      "hasFloodRisk": false,
      "hasLandslideRisk": true,
      "note": "土砂災害警戒区域あり",
      "source": "国土数値情報（reinfolib XKT026/029）",
      "asOf": "2024"
    },
    "amenities": {
      "stations": 1,
      "preschools": 0,
      "medicalFacilities": 22,
      "source": "国土数値情報（reinfolib XKT015/007/010）",
      "asOf": "令和5年度"
    }
  },
  {
    "code": "23446",
    "pref": "aichi",
    "name": "美浜町",
    "population": 20504,
    "populationTrend": "減少",
    "rent": {
      "value": 33963,
      "unit": "円/月",
      "source": "住宅・土地統計調査（加重平均）",
      "asOf": "2023",
      "isEstimated": false
    },
    "landPrice": {
      "value": 24029,
      "unit": "円/㎡",
      "source": "地価公示（住宅地平均）",
      "asOf": "2025",
      "isEstimated": false
    },
    "waitlistChildren": {
      "value": 0,
      "unit": "人",
      "source": "こども家庭庁 保育所等関連状況取りまとめ",
      "asOf": "2024-04-01",
      "isEstimated": false
    },
    "hazard": {
      "hasFloodRisk": false,
      "hasLandslideRisk": true,
      "note": "土砂災害警戒区域あり",
      "source": "国土数値情報（reinfolib XKT026/029）",
      "asOf": "2024"
    },
    "amenities": {
      "stations": 6,
      "preschools": 1,
      "medicalFacilities": 19,
      "source": "国土数値情報（reinfolib XKT015/007/010）",
      "asOf": "令和5年度"
    }
  },
  {
    "code": "23447",
    "pref": "aichi",
    "name": "武豊町",
    "population": 42921,
    "populationTrend": "微減",
    "rent": {
      "value": 46633,
      "unit": "円/月",
      "source": "住宅・土地統計調査（加重平均）",
      "asOf": "2023",
      "isEstimated": false
    },
    "landPrice": {
      "value": 54700,
      "unit": "円/㎡",
      "source": "地価公示（住宅地平均）",
      "asOf": "2025",
      "isEstimated": false
    },
    "waitlistChildren": {
      "value": 0,
      "unit": "人",
      "source": "こども家庭庁 保育所等関連状況取りまとめ",
      "asOf": "2024-04-01",
      "isEstimated": false
    },
    "hazard": {
      "hasFloodRisk": true,
      "hasLandslideRisk": true,
      "note": "浸水想定区域あり / 土砂災害警戒区域あり",
      "source": "国土数値情報（reinfolib XKT026/029）",
      "asOf": "2024"
    },
    "amenities": {
      "stations": 5,
      "preschools": 1,
      "medicalFacilities": 40,
      "source": "国土数値情報（reinfolib XKT015/007/010）",
      "asOf": "令和5年度"
    }
  },
  {
    "code": "23501",
    "pref": "aichi",
    "name": "幸田町",
    "population": 41591,
    "populationTrend": "微減",
    "rent": {
      "value": 56598,
      "unit": "円/月",
      "source": "住宅・土地統計調査（加重平均）",
      "asOf": "2023",
      "isEstimated": false
    },
    "landPrice": {
      "value": 82461,
      "unit": "円/㎡",
      "source": "地価公示（住宅地平均）",
      "asOf": "2025",
      "isEstimated": false
    },
    "waitlistChildren": {
      "value": 0,
      "unit": "人",
      "source": "こども家庭庁 保育所等関連状況取りまとめ",
      "asOf": "2024-04-01",
      "isEstimated": false
    },
    "hazard": {
      "hasFloodRisk": true,
      "hasLandslideRisk": true,
      "note": "浸水想定区域あり / 土砂災害警戒区域あり",
      "source": "国土数値情報（reinfolib XKT026/029）",
      "asOf": "2024"
    },
    "amenities": {
      "stations": 3,
      "preschools": 4,
      "medicalFacilities": 42,
      "source": "国土数値情報（reinfolib XKT015/007/010）",
      "asOf": "令和5年度"
    }
  },
  {
    "code": "23561",
    "pref": "aichi",
    "name": "設楽町",
    "population": 3929,
    "populationTrend": "減少",
    "rent": {
      "value": 0,
      "unit": "円/月",
      "source": "サンプル",
      "asOf": "-",
      "isEstimated": true
    },
    "landPrice": {
      "value": 0,
      "unit": "円/㎡",
      "source": "サンプル",
      "asOf": "-",
      "isEstimated": true
    },
    "waitlistChildren": {
      "value": 0,
      "unit": "人",
      "source": "こども家庭庁 保育所等関連状況取りまとめ",
      "asOf": "2024-04-01",
      "isEstimated": false
    },
    "hazard": {
      "hasFloodRisk": false,
      "hasLandslideRisk": true,
      "note": "土砂災害警戒区域あり",
      "source": "国土数値情報（reinfolib XKT026/029）",
      "asOf": "2024"
    },
    "amenities": {
      "stations": 0,
      "preschools": 0,
      "medicalFacilities": 11,
      "source": "国土数値情報（reinfolib XKT015/007/010）",
      "asOf": "令和5年度"
    }
  },
  {
    "code": "23562",
    "pref": "aichi",
    "name": "東栄町",
    "population": 2464,
    "populationTrend": "減少",
    "rent": {
      "value": 0,
      "unit": "円/月",
      "source": "サンプル",
      "asOf": "-",
      "isEstimated": true
    },
    "landPrice": {
      "value": 0,
      "unit": "円/㎡",
      "source": "サンプル",
      "asOf": "-",
      "isEstimated": true
    },
    "waitlistChildren": {
      "value": 0,
      "unit": "人",
      "source": "こども家庭庁 保育所等関連状況取りまとめ",
      "asOf": "2024-04-01",
      "isEstimated": false
    },
    "hazard": {
      "hasFloodRisk": false,
      "hasLandslideRisk": true,
      "note": "土砂災害警戒区域あり",
      "source": "国土数値情報（reinfolib XKT026/029）",
      "asOf": "2024"
    },
    "amenities": {
      "stations": 2,
      "preschools": 0,
      "medicalFacilities": 5,
      "source": "国土数値情報（reinfolib XKT015/007/010）",
      "asOf": "令和5年度"
    }
  },
  {
    "code": "23563",
    "pref": "aichi",
    "name": "豊根村",
    "population": 835,
    "populationTrend": "減少",
    "rent": {
      "value": 0,
      "unit": "円/月",
      "source": "サンプル",
      "asOf": "-",
      "isEstimated": true
    },
    "landPrice": {
      "value": 0,
      "unit": "円/㎡",
      "source": "サンプル",
      "asOf": "-",
      "isEstimated": true
    },
    "waitlistChildren": {
      "value": 0,
      "unit": "人",
      "source": "こども家庭庁 保育所等関連状況取りまとめ",
      "asOf": "2024-04-01",
      "isEstimated": false
    },
    "hazard": {
      "hasFloodRisk": false,
      "hasLandslideRisk": true,
      "note": "土砂災害警戒区域あり",
      "source": "国土数値情報（reinfolib XKT026/029）",
      "asOf": "2024"
    },
    "amenities": {
      "stations": 0,
      "preschools": 0,
      "medicalFacilities": 3,
      "source": "国土数値情報（reinfolib XKT015/007/010）",
      "asOf": "令和5年度"
    }
  }
]
